file_label_tools/__init__.py
file_label_tools/__main__.py
file_label_tools/cli.py
file_label_tools/config.py
file_label_tools/database.py
file_label_tools/paths.py
file_label_tools/webapp.py
file_label_tools/static/css/style.css
file_label_tools/static/js/back_to_top.js
file_label_tools/static/js/chart.js
file_label_tools/static/js/chart2.js
file_label_tools/static/js/chartjs-plugin-datalabels@2.js
file_label_tools/static/js/label.js
file_label_tools/static/js/main.js
file_label_tools/static/js/preview.js
file_label_tools/static/js/project.js
file_label_tools/templates/index.html
file_label_tools/templates/label.html
file_label_tools/templates/login.html
file_label_tools/templates/main.html
file_label_tools/templates/preview.html
file_labeler-1.0.0.dist-info/licenses/LICENSE
file_labeler-1.0.0.dist-info/METADATA
file_labeler-1.0.0.dist-info/WHEEL
file_labeler-1.0.0.dist-info/entry_points.txt
file_labeler-1.0.0.dist-info/top_level.txt
file_labeler-1.0.0.dist-info/RECORD
