Metadata-Version: 2.4
Name: file-labeler
Version: 1.0.0
Summary: A Flask-based file labeling web tool.
Author: dreamer
License-Expression: MIT
Project-URL: Homepage, https://example.invalid/file-label-tools
Requires-Python: >=3.9
License-File: LICENSE
Requires-Dist: Flask>=3.0.0
Requires-Dist: Werkzeug>=3.0.1
Requires-Dist: platformdirs>=4.0.0
Dynamic: license-file
